{
  "card_type": 9,
  "itemid": "1076033053424305_-_3511504656108155",
  "mblog": {
    "_created_at": 1352691414,
    "attitudes_count": 13,
    "bid": "z4PhTpD0D",
    "comments_count": 92,
    "created_at": "2012-11-12 11:36",
    "favorited": false,
    "id": "3511504656108155",
    "isLongText": false,
    "mblogtype": 0,
    "raw_text": "系统自动转发。求别黑。T^T",
    "reposts_count": 13,
    "retweeted_status": {
      "attitudes_count": 32,
      "bid": "z4P9PFeqE",
      "bmiddle_pic": "http://ww3.sinaimg.cn/bmiddle/a04b2a1dtw1dys39xjcxfj.jpg",
      "comments_count": 212,
      "created_at": "2012-11-12 11:17",
      "favorited": false,
      "id": "3511499659826916",
      "isLongText": false,
      "original_pic": "http://ww3.sinaimg.cn/large/a04b2a1dtw1dys39xjcxfj.jpg",
      "pics": [
        {
          "geo": false,
          "large": {
            "geo": false,
            "size": "large",
            "url": "http://ww3.sinaimg.cn/large/a04b2a1dtw1dys39xjcxfj.jpg"
          },
          "pid": "a04b2a1dtw1dys39xjcxfj",
          "size": "orj360",
          "url": "http://ww3.sinaimg.cn/orj360/a04b2a1dtw1dys39xjcxfj.jpg"
        }
      ],
      "reposts_count": 1034,
      "source": "微博 weibo.com",
      "text": "【SNH48新官网上线 成员公式照公布】SNH48官方网站及官方论坛于2012年11月12日以全新的面貌和大家见面！同时，让粉丝们期待已久的28名SNH48一期生公式照及成员简介也会同时上线，想要知道更多资讯和成员信息，请随时关注SNH48官网：<a data-url=\"http://t.cn/zOWq89R\" target=\"_blank\" href=\"http://weibo.cn/sinaurl?url_type=39&object_type=webpage&pos=1&luicode=10000011&lfid=1076033053424305&u=http%3A%2F%2Fwww.snh48.com%2F%3Furl_type%3D39%26object_type%3Dwebpage%26pos%3D1&ep=z4P9PFeqE%2C2689280541%2Cz4P9PFeqE%2C2689280541\" class=\"\"><span class=\"url-icon\"><img src=\"//h5.sinaimg.cn/upload/2015/09/25/3/timeline_card_small_web_default.png\"></span></i><span class=\"surl-text\">中国大型女子偶像组合SNH48——AKB48全球姐妹团体——SNH48中国官方网站</a> 官方论坛：<a data-url=\"http://t.cn/zj7SzNr\" target=\"_blank\" href=\"http://weibo.cn/sinaurl?url_type=39&object_type=webpage&pos=1&luicode=10000011&lfid=1076033053424305&u=http%3A%2F%2Fclub.snh48.com%2Fforum.php%3Furl_type%3D39%26object_type%3Dwebpage%26pos%3D1&ep=z4P9PFeqE%2C2689280541%2Cz4P9PFeqE%2C2689280541\" class=\"\"><span class=\"url-icon\"><img src=\"//h5.sinaimg.cn/upload/2015/09/25/3/timeline_card_small_web_default.png\"></span></i><span class=\"surl-text\">SNH48官方粉丝俱乐部 -  Powered by Discuz!</a> ​​​",
      "thumbnail_pic": "http://ww3.sinaimg.cn/thumbnail/a04b2a1dtw1dys39xjcxfj.jpg",
      "user": {
        "cover_image_phone": "http://wx3.sinaimg.cn/crop.0.0.640.640.640/a04b2a1dly1fays2ry9chj20ku0kuwi00.jpg",
        "description": "大家好，我们是大型女子偶像组合SNH48。感谢您对我们的支持与关注！客服电话：400-617-6598 。客服服务时间：7x24小时",
        "follow_count": 382,
        "follow_me": false,
        "followers_count": 4740360,
        "following": false,
        "gender": "f",
        "id": 2689280541,
        "mbrank": 6,
        "mbtype": 11,
        "profile_image_url": "http://tva2.sinaimg.cn/crop.0.0.180.180.180/a04b2a1djw8elz2yidkv7j20500503yg.jpg",
        "profile_url": "http://m.weibo.cn/u/2689280541?uid=2689280541&luicode=10000011&lfid=1076033053424305",
        "screen_name": "SNH48",
        "statuses_count": 12603,
        "urank": 40,
        "verified": true,
        "verified_reason": "SNH48团体官方微博",
        "verified_type": 0,
        "verified_type_ext": 1
      },
      "visible": {
        "list_id": 0,
        "type": 0
      }
    },
    "source": "Android客户端",
    "text": "系统自动转发。求别黑。T^T",
    "user": {
      "cover_image_phone": "http://ww1.sinaimg.cn/crop.0.0.640.640.640/549d0121tw1egm1kjly3jj20hs0hsq4f.jpg",
      "description": "momo哒！~合作联系，商务：business@snh48.com 021-66075351 影视：yingshi@snh48.com 021-66078718*819 综艺：zongyi@snh48.com 021-66078718*821",
      "follow_count": 201,
      "follow_me": false,
      "followers_count": 475619,
      "following": false,
      "gender": "f",
      "id": 3053424305,
      "mbrank": 6,
      "mbtype": 12,
      "profile_image_url": "http://tva4.sinaimg.cn/crop.6.0.499.499.180/b5ff8eb1jw8f9g0xrj1doj20e80dvdg7.jpg",
      "profile_url": "http://m.weibo.cn/u/3053424305?uid=3053424305&luicode=10000011&lfid=1076033053424305",
      "screen_name": "SNH48-莫寒",
      "statuses_count": 1910,
      "urank": 37,
      "verified": true,
      "verified_reason": "人气偶像团体SNH48成员 莫寒",
      "verified_type": 0,
      "verified_type_ext": 0
    },
    "visible": {
      "list_id": 0,
      "type": 0
    }
  },
  "openurl": "",
  "scheme": "http://m.weibo.cn/status/z4PhTpD0D?mblogid=z4PhTpD0D&luicode=10000011&lfid=1076033053424305",
  "show_type": 0
}