{
  "card_type": 9,
  "itemid": "1076033053424305_-_3547338213522424",
  "mblog": {
    "_created_at": 1361234799,
    "attitudes_count": 24,
    "bid": "zjRtXeMli",
    "bmiddle_pic": "http://ww2.sinaimg.cn/bmiddle/b5ff8eb1jw1e1yf9zrcblj.jpg",
    "comments_count": 121,
    "created_at": "2013-02-19 08:46",
    "favorited": false,
    "id": "3547338213522424",
    "isLongText": false,
    "mblogtype": 0,
    "original_pic": "http://ww2.sinaimg.cn/large/b5ff8eb1jw1e1yf9zrcblj.jpg",
    "pics": [
      {
        "geo": false,
        "large": {
          "geo": false,
          "size": "large",
          "url": "http://ww2.sinaimg.cn/large/b5ff8eb1jw1e1yf9zrcblj.jpg"
        },
        "pid": "b5ff8eb1jw1e1yf9zrcblj",
        "size": "orj360",
        "url": "http://ww2.sinaimg.cn/orj360/b5ff8eb1jw1e1yf9zrcblj.jpg"
      }
    ],
    "reposts_count": 13,
    "source": "索尼Xperia SL LT26ii",
    "text": "假期的最后在家时刻。好舍不得。爸爸妈妈抱住！这个图有木有很眼熟~就是要用来对比的！我明明比大一瘦为嘛觉得脸更圆了！想逆生长也不是这么逆的！那个时候的我真是无法直视啊。。。随意吐槽吧！我不会说第一次cos图比那个更糟糕的！然后我看到了我百科里那个职业空大选手。。快出来承认是谁写的！盯~ ​​​",
    "thumbnail_pic": "http://ww2.sinaimg.cn/thumbnail/b5ff8eb1jw1e1yf9zrcblj.jpg",
    "user": {
      "cover_image_phone": "http://ww1.sinaimg.cn/crop.0.0.640.640.640/549d0121tw1egm1kjly3jj20hs0hsq4f.jpg",
      "description": "momo哒！~合作联系，商务：business@snh48.com 021-66075351 影视：yingshi@snh48.com 021-66078718*819 综艺：zongyi@snh48.com 021-66078718*821",
      "follow_count": 201,
      "follow_me": false,
      "followers_count": 475619,
      "following": false,
      "gender": "f",
      "id": 3053424305,
      "mbrank": 6,
      "mbtype": 12,
      "profile_image_url": "http://tva4.sinaimg.cn/crop.6.0.499.499.180/b5ff8eb1jw8f9g0xrj1doj20e80dvdg7.jpg",
      "profile_url": "http://m.weibo.cn/u/3053424305?uid=3053424305&luicode=10000011&lfid=1076033053424305",
      "screen_name": "SNH48-莫寒",
      "statuses_count": 1910,
      "urank": 37,
      "verified": true,
      "verified_reason": "人气偶像团体SNH48成员 莫寒",
      "verified_type": 0,
      "verified_type_ext": 0
    },
    "visible": {
      "list_id": 0,
      "type": 0
    }
  },
  "openurl": "",
  "scheme": "http://m.weibo.cn/status/zjRtXeMli?mblogid=zjRtXeMli&luicode=10000011&lfid=1076033053424305",
  "show_type": 0
}