{
  "card_type": 9,
  "itemid": "1076033053424305_-_3752907985766981",
  "mblog": {
    "_created_at": 1410246452,
    "attitudes_count": 236,
    "bid": "BmcnsocfP",
    "bmiddle_pic": "http://ww2.sinaimg.cn/bmiddle/b5ff8eb1gw1ek68mzkqhwj20gj0ne0zi.jpg",
    "comments_count": 46,
    "created_at": "2014-09-09 15:07",
    "favorited": false,
    "id": "3752907985766981",
    "isLongText": false,
    "mblogtype": 0,
    "original_pic": "http://ww2.sinaimg.cn/large/b5ff8eb1gw1ek68mzkqhwj20gj0ne0zi.jpg",
    "page_info": {
      "content1": "",
      "content2": "",
      "page_pic": {
        "url": "http://ww4.sinaimg.cn/thumb180/74f67c55jw9ey1pjmhxcbj2050050748.jpg"
      },
      "page_title": "#东芝×SNH48#",
      "page_url": "http://weibo.cn/sinaurl?containerid=100808afe9ea60bd417073be3c1bbddf056a73&extparam=%E4%B8%9C%E8%8A%9D%C3%97SNH48&luicode=10000011&lfid=1076033053424305&u=http%3A%2F%2Fm.weibo.cn%2Fp%2Findex%3Fcontainerid%3D100808afe9ea60bd417073be3c1bbddf056a73%26extparam%3D%25E4%25B8%259C%25E8%258A%259D%25C3%2597SNH48%26luicode%3D10000011%26lfid%3D1076033053424305",
      "type": "topic"
    },
    "pics": [
      {
        "geo": {
          "croped": false,
          "height": 509,
          "width": 360
        },
        "large": {
          "geo": {
            "croped": false,
            "height": "842",
            "width": "595"
          },
          "size": "large",
          "url": "http://ww2.sinaimg.cn/large/b5ff8eb1gw1ek68mzkqhwj20gj0ne0zi.jpg"
        },
        "pid": "b5ff8eb1gw1ek68mzkqhwj20gj0ne0zi",
        "size": "orj360",
        "url": "http://ww2.sinaimg.cn/orj360/b5ff8eb1gw1ek68mzkqhwj20gj0ne0zi.jpg"
      }
    ],
    "reposts_count": 21,
    "source": "微博 weibo.com",
    "text": "#东芝×SNH48#9月27日（周六）东芝将举办FlashAir presents SNH48特别演出活动！！9月16日-25日，门票将在官网销售，随票还将附赠FlashAir（8GB）存储卡一张，仅需128元！届时到场观众还将有机会获得一份惊喜奖品！详情请登录官网：<a data-url=\"http://t.cn/zOWq89R\" target=\"_blank\" href=\"http://weibo.cn/sinaurl?url_type=39&object_type=webpage&pos=1&luicode=10000011&lfid=1076033053424305&u=http%3A%2F%2Fwww.snh48.com%2F%3Furl_type%3D39%26object_type%3Dwebpage%26pos%3D1&ep=BmcnsocfP%2C3053424305%2CBmcnsocfP%2C3053424305\" class=\"\"><span class=\"url-icon\"><img src=\"//h5.sinaimg.cn/upload/2015/09/25/3/timeline_card_small_web_default.png\"></span></i><span class=\"surl-text\">中国大型女子偶像组合SNH48——AKB48全球姐妹团体——SNH48中国官方网站</a> ​​​",
    "thumbnail_pic": "http://ww2.sinaimg.cn/thumbnail/b5ff8eb1gw1ek68mzkqhwj20gj0ne0zi.jpg",
    "user": {
      "cover_image_phone": "http://ww1.sinaimg.cn/crop.0.0.640.640.640/549d0121tw1egm1kjly3jj20hs0hsq4f.jpg",
      "description": "momo哒！~合作联系，商务：business@snh48.com 021-66075351 影视：yingshi@snh48.com 021-66078718*819 综艺：zongyi@snh48.com 021-66078718*821",
      "follow_count": 201,
      "follow_me": false,
      "followers_count": 475619,
      "following": false,
      "gender": "f",
      "id": 3053424305,
      "mbrank": 6,
      "mbtype": 12,
      "profile_image_url": "http://tva4.sinaimg.cn/crop.6.0.499.499.180/b5ff8eb1jw8f9g0xrj1doj20e80dvdg7.jpg",
      "profile_url": "http://m.weibo.cn/u/3053424305?uid=3053424305&luicode=10000011&lfid=1076033053424305",
      "screen_name": "SNH48-莫寒",
      "statuses_count": 1910,
      "urank": 37,
      "verified": true,
      "verified_reason": "人气偶像团体SNH48成员 莫寒",
      "verified_type": 0,
      "verified_type_ext": 0
    },
    "visible": {
      "list_id": 0,
      "type": 0
    }
  },
  "openurl": "",
  "scheme": "http://m.weibo.cn/status/BmcnsocfP?mblogid=BmcnsocfP&luicode=10000011&lfid=1076033053424305",
  "show_type": 0
}