{
  "card_type": 9,
  "itemid": "1076033053424305_-_3917769730573691",
  "mblog": {
    "_created_at": 1449552555,
    "attitudes_count": 1635,
    "bid": "D7sgR2pf5",
    "bmiddle_pic": "http://ww2.sinaimg.cn/bmiddle/b5ff8eb1gw1eys6pimemvj20cp0hsjui.jpg",
    "cardid": "vip_002",
    "comments_count": 320,
    "created_at": "2015-12-08 13:29",
    "favorited": false,
    "id": "3917769730573691",
    "isLongText": false,
    "mblogtype": 0,
    "original_pic": "http://ww2.sinaimg.cn/large/b5ff8eb1gw1eys6pimemvj20cp0hsjui.jpg",
    "page_info": {
      "content1": "",
      "content2": "",
      "page_pic": {
        "url": "http://ww1.sinaimg.cn/thumbnail/5b7d5234gw1evx5v9kqp4j2050050glz.jpg"
      },
      "page_title": "#上海哈利波特展#",
      "page_url": "http://weibo.cn/sinaurl?containerid=100808a20603df56dbfa7be7d2f2271c5d7f34&extparam=%E4%B8%8A%E6%B5%B7%E5%93%88%E5%88%A9%E6%B3%A2%E7%89%B9%E5%B1%95&luicode=10000011&lfid=1076033053424305&u=http%3A%2F%2Fm.weibo.cn%2Fp%2Findex%3Fcontainerid%3D100808a20603df56dbfa7be7d2f2271c5d7f34%26extparam%3D%25E4%25B8%258A%25E6%25B5%25B7%25E5%2593%2588%25E5%2588%25A9%25E6%25B3%25A2%25E7%2589%25B9%25E5%25B1%2595%26luicode%3D10000011%26lfid%3D1076033053424305",
      "type": "topic"
    },
    "pics": [
      {
        "geo": {
          "croped": false,
          "height": 504,
          "width": 360
        },
        "large": {
          "geo": {
            "croped": false,
            "height": "640",
            "width": "457"
          },
          "size": "large",
          "url": "http://ww2.sinaimg.cn/large/b5ff8eb1gw1eys6pimemvj20cp0hsjui.jpg"
        },
        "pid": "b5ff8eb1gw1eys6pimemvj20cp0hsjui",
        "size": "orj360",
        "url": "http://ww2.sinaimg.cn/orj360/b5ff8eb1gw1eys6pimemvj20cp0hsjui.jpg"
      },
      {
        "geo": {
          "croped": false,
          "height": 499,
          "width": 360
        },
        "large": {
          "geo": {
            "croped": false,
            "height": "640",
            "width": "461"
          },
          "size": "large",
          "url": "http://ww3.sinaimg.cn/large/b5ff8eb1gw1eys6plhqqej20ct0hsad1.jpg"
        },
        "pid": "b5ff8eb1gw1eys6plhqqej20ct0hsad1",
        "size": "orj360",
        "url": "http://ww3.sinaimg.cn/orj360/b5ff8eb1gw1eys6plhqqej20ct0hsad1.jpg"
      },
      {
        "geo": {
          "croped": false,
          "height": 499,
          "width": 360
        },
        "large": {
          "geo": {
            "croped": false,
            "height": "640",
            "width": "461"
          },
          "size": "large",
          "url": "http://ww4.sinaimg.cn/large/b5ff8eb1gw1eys6pk91opj20ct0hsad5.jpg"
        },
        "pid": "b5ff8eb1gw1eys6pk91opj20ct0hsad5",
        "size": "orj360",
        "url": "http://ww4.sinaimg.cn/orj360/b5ff8eb1gw1eys6pk91opj20ct0hsad5.jpg"
      },
      {
        "geo": {
          "croped": false,
          "height": 499,
          "width": 360
        },
        "large": {
          "geo": {
            "croped": false,
            "height": "640",
            "width": "461"
          },
          "size": "large",
          "url": "http://ww3.sinaimg.cn/large/b5ff8eb1gw1eys6pmyno8j20ct0hsdii.jpg"
        },
        "pid": "b5ff8eb1gw1eys6pmyno8j20ct0hsdii",
        "size": "orj360",
        "url": "http://ww3.sinaimg.cn/orj360/b5ff8eb1gw1eys6pmyno8j20ct0hsdii.jpg"
      },
      {
        "geo": {
          "croped": false,
          "height": 517,
          "width": 360
        },
        "large": {
          "geo": {
            "croped": false,
            "height": "640",
            "width": "445"
          },
          "size": "large",
          "url": "http://ww2.sinaimg.cn/large/b5ff8eb1gw1eys6poevoxj20cd0hsgno.jpg"
        },
        "pid": "b5ff8eb1gw1eys6poevoxj20cd0hsgno",
        "size": "orj360",
        "url": "http://ww2.sinaimg.cn/orj360/b5ff8eb1gw1eys6poevoxj20cd0hsgno.jpg"
      },
      {
        "geo": {
          "croped": false,
          "height": 499,
          "width": 360
        },
        "large": {
          "geo": {
            "croped": false,
            "height": "640",
            "width": "461"
          },
          "size": "large",
          "url": "http://ww4.sinaimg.cn/large/b5ff8eb1gw1eys6pxijvpj20ct0hsack.jpg"
        },
        "pid": "b5ff8eb1gw1eys6pxijvpj20ct0hsack",
        "size": "orj360",
        "url": "http://ww4.sinaimg.cn/orj360/b5ff8eb1gw1eys6pxijvpj20ct0hsack.jpg"
      },
      {
        "geo": {
          "croped": false,
          "height": 504,
          "width": 360
        },
        "large": {
          "geo": {
            "croped": false,
            "height": "640",
            "width": "457"
          },
          "size": "large",
          "url": "http://ww1.sinaimg.cn/large/b5ff8eb1gw1eys6pynq9xj20cp0hswgb.jpg"
        },
        "pid": "b5ff8eb1gw1eys6pynq9xj20cp0hswgb",
        "size": "orj360",
        "url": "http://ww1.sinaimg.cn/orj360/b5ff8eb1gw1eys6pynq9xj20cp0hswgb.jpg"
      },
      {
        "geo": {
          "croped": false,
          "height": 504,
          "width": 360
        },
        "large": {
          "geo": {
            "croped": false,
            "height": "640",
            "width": "457"
          },
          "size": "large",
          "url": "http://ww1.sinaimg.cn/large/b5ff8eb1gw1eys6q0qqvnj20cp0hstbg.jpg"
        },
        "pid": "b5ff8eb1gw1eys6q0qqvnj20cp0hstbg",
        "size": "orj360",
        "url": "http://ww1.sinaimg.cn/orj360/b5ff8eb1gw1eys6q0qqvnj20cp0hstbg.jpg"
      },
      {
        "geo": {
          "croped": false,
          "height": 499,
          "width": 360
        },
        "large": {
          "geo": {
            "croped": false,
            "height": "640",
            "width": "461"
          },
          "size": "large",
          "url": "http://ww2.sinaimg.cn/large/b5ff8eb1gw1eys6pw76irj20ct0hsgo6.jpg"
        },
        "pid": "b5ff8eb1gw1eys6pw76irj20ct0hsgo6",
        "size": "orj360",
        "url": "http://ww2.sinaimg.cn/orj360/b5ff8eb1gw1eys6pw76irj20ct0hsgo6.jpg"
      }
    ],
    "reposts_count": 158,
    "source": "塞纳河傲天iPhone",
    "text": "那一年给我送信的那只笨蛋猫头鹰，到底迷路去哪里了？…怎么……还没有来呢………○○（＞＜）○○<a class='k' href='http://m.weibo.cn/k/上海哈利波特展?from=feed'>#上海哈利波特展#</a><a class='k' href='http://m.weibo.cn/k/HP?from=feed'>#HP#</a>#哈利·波特# ​​​",
    "thumbnail_pic": "http://ww2.sinaimg.cn/thumbnail/b5ff8eb1gw1eys6pimemvj20cp0hsjui.jpg",
    "user": {
      "cover_image_phone": "http://ww1.sinaimg.cn/crop.0.0.640.640.640/549d0121tw1egm1kjly3jj20hs0hsq4f.jpg",
      "description": "momo哒！~合作联系，商务：business@snh48.com 021-66075351 影视：yingshi@snh48.com 021-66078718*819 综艺：zongyi@snh48.com 021-66078718*821",
      "follow_count": 201,
      "follow_me": false,
      "followers_count": 475619,
      "following": false,
      "gender": "f",
      "id": 3053424305,
      "mbrank": 6,
      "mbtype": 12,
      "profile_image_url": "http://tva4.sinaimg.cn/crop.6.0.499.499.180/b5ff8eb1jw8f9g0xrj1doj20e80dvdg7.jpg",
      "profile_url": "http://m.weibo.cn/u/3053424305?uid=3053424305&luicode=10000011&lfid=1076033053424305",
      "screen_name": "SNH48-莫寒",
      "statuses_count": 1910,
      "urank": 37,
      "verified": true,
      "verified_reason": "人气偶像团体SNH48成员 莫寒",
      "verified_type": 0,
      "verified_type_ext": 0
    },
    "visible": {
      "list_id": 0,
      "type": 0
    }
  },
  "openurl": "",
  "scheme": "http://m.weibo.cn/status/D7sgR2pf5?mblogid=D7sgR2pf5&luicode=10000011&lfid=1076033053424305",
  "show_type": 0
}