{
  "card_type": 9,
  "itemid": "1076033053424305_-_3921893998975122",
  "mblog": {
    "_created_at": 1450535857,
    "attitudes_count": 2268,
    "bid": "D9byTBEQ2",
    "bmiddle_pic": "http://ww4.sinaimg.cn/bmiddle/b5ff8eb1gw1ez5ceoiuqmj20dc0hsjth.jpg",
    "cardid": "vip_002",
    "comments_count": 403,
    "created_at": "2015-12-19 22:37",
    "favorited": false,
    "id": "3921893998975122",
    "isLongText": false,
    "mblogtype": 0,
    "original_pic": "http://ww4.sinaimg.cn/large/b5ff8eb1gw1ez5ceoiuqmj20dc0hsjth.jpg",
    "page_info": {
      "content1": "",
      "content2": "",
      "page_pic": {
        "url": "http://wx2.sinaimg.cn/thumbnail/719d0099ly1fb7ncwf9ovj20500503yv0.jpg"
      },
      "page_title": "#圣诞快乐#",
      "page_url": "http://weibo.cn/sinaurl?containerid=100808d4fa2f90eb370f7d3429eddf72a5d900&extparam=%E5%9C%A3%E8%AF%9E%E5%BF%AB%E4%B9%90&luicode=10000011&lfid=1076033053424305&u=http%3A%2F%2Fm.weibo.cn%2Fp%2Findex%3Fcontainerid%3D100808d4fa2f90eb370f7d3429eddf72a5d900%26extparam%3D%25E5%259C%25A3%25E8%25AF%259E%25E5%25BF%25AB%25E4%25B9%2590%26luicode%3D10000011%26lfid%3D1076033053424305",
      "type": "topic"
    },
    "pics": [
      {
        "geo": {
          "croped": false,
          "height": 480,
          "width": 360
        },
        "large": {
          "geo": {
            "croped": false,
            "height": "640",
            "width": "480"
          },
          "size": "large",
          "url": "http://ww4.sinaimg.cn/large/b5ff8eb1gw1ez5ceoiuqmj20dc0hsjth.jpg"
        },
        "pid": "b5ff8eb1gw1ez5ceoiuqmj20dc0hsjth",
        "size": "orj360",
        "url": "http://ww4.sinaimg.cn/orj360/b5ff8eb1gw1ez5ceoiuqmj20dc0hsjth.jpg"
      },
      {
        "geo": {
          "croped": false,
          "height": 480,
          "width": 360
        },
        "large": {
          "geo": {
            "croped": false,
            "height": "640",
            "width": "480"
          },
          "size": "large",
          "url": "http://ww4.sinaimg.cn/large/b5ff8eb1gw1ez5ceoyek1j20dc0hswgv.jpg"
        },
        "pid": "b5ff8eb1gw1ez5ceoyek1j20dc0hswgv",
        "size": "orj360",
        "url": "http://ww4.sinaimg.cn/orj360/b5ff8eb1gw1ez5ceoyek1j20dc0hswgv.jpg"
      },
      {
        "geo": {
          "croped": false,
          "height": 480,
          "width": 360
        },
        "large": {
          "geo": {
            "croped": false,
            "height": "640",
            "width": "480"
          },
          "size": "large",
          "url": "http://ww1.sinaimg.cn/large/b5ff8eb1gw1ez5ceny9obj20dc0hswgt.jpg"
        },
        "pid": "b5ff8eb1gw1ez5ceny9obj20dc0hswgt",
        "size": "orj360",
        "url": "http://ww1.sinaimg.cn/orj360/b5ff8eb1gw1ez5ceny9obj20dc0hswgt.jpg"
      },
      {
        "geo": {
          "croped": false,
          "height": 480,
          "width": 360
        },
        "large": {
          "geo": {
            "croped": false,
            "height": "640",
            "width": "480"
          },
          "size": "large",
          "url": "http://ww2.sinaimg.cn/large/b5ff8eb1gw1ez5cepk53kj20dc0hs40l.jpg"
        },
        "pid": "b5ff8eb1gw1ez5cepk53kj20dc0hs40l",
        "size": "orj360",
        "url": "http://ww2.sinaimg.cn/orj360/b5ff8eb1gw1ez5cepk53kj20dc0hs40l.jpg"
      },
      {
        "geo": {
          "croped": false,
          "height": 480,
          "width": 360
        },
        "large": {
          "geo": {
            "croped": false,
            "height": "640",
            "width": "480"
          },
          "size": "large",
          "url": "http://ww3.sinaimg.cn/large/b5ff8eb1gw1ez5ceq0x66j20dc0hsac3.jpg"
        },
        "pid": "b5ff8eb1gw1ez5ceq0x66j20dc0hsac3",
        "size": "orj360",
        "url": "http://ww3.sinaimg.cn/orj360/b5ff8eb1gw1ez5ceq0x66j20dc0hsac3.jpg"
      },
      {
        "geo": {
          "croped": false,
          "height": 480,
          "width": 360
        },
        "large": {
          "geo": {
            "croped": false,
            "height": "640",
            "width": "480"
          },
          "size": "large",
          "url": "http://ww1.sinaimg.cn/large/b5ff8eb1gw1ez5ceqhnj0j20dc0hs76c.jpg"
        },
        "pid": "b5ff8eb1gw1ez5ceqhnj0j20dc0hs76c",
        "size": "orj360",
        "url": "http://ww1.sinaimg.cn/orj360/b5ff8eb1gw1ez5ceqhnj0j20dc0hs76c.jpg"
      },
      {
        "geo": {
          "croped": false,
          "height": 480,
          "width": 360
        },
        "large": {
          "geo": {
            "croped": false,
            "height": "640",
            "width": "480"
          },
          "size": "large",
          "url": "http://ww2.sinaimg.cn/large/b5ff8eb1gw1ez5cer4dvmj20dc0hsac9.jpg"
        },
        "pid": "b5ff8eb1gw1ez5cer4dvmj20dc0hsac9",
        "size": "orj360",
        "url": "http://ww2.sinaimg.cn/orj360/b5ff8eb1gw1ez5cer4dvmj20dc0hsac9.jpg"
      },
      {
        "geo": {
          "croped": false,
          "height": 480,
          "width": 360
        },
        "large": {
          "geo": {
            "croped": false,
            "height": "640",
            "width": "480"
          },
          "size": "large",
          "url": "http://ww1.sinaimg.cn/large/b5ff8eb1gw1ez5cernqxlj20dc0hs0v2.jpg"
        },
        "pid": "b5ff8eb1gw1ez5cernqxlj20dc0hs0v2",
        "size": "orj360",
        "url": "http://ww1.sinaimg.cn/orj360/b5ff8eb1gw1ez5cernqxlj20dc0hs0v2.jpg"
      },
      {
        "geo": {
          "croped": false,
          "height": 480,
          "width": 360
        },
        "large": {
          "geo": {
            "croped": false,
            "height": "640",
            "width": "480"
          },
          "size": "large",
          "url": "http://ww1.sinaimg.cn/large/b5ff8eb1gw1ez5ces56zrj20dc0hstb2.jpg"
        },
        "pid": "b5ff8eb1gw1ez5ces56zrj20dc0hstb2",
        "size": "orj360",
        "url": "http://ww1.sinaimg.cn/orj360/b5ff8eb1gw1ez5ces56zrj20dc0hstb2.jpg"
      }
    ],
    "reposts_count": 209,
    "source": "ᙏ̤̫͚\" iPhone",
    "text": "原来今天是我今年最后一场公演啊…u´꓃`u我为什么要在这种神奇的氛围中度过啊………uＴｪＴu收回今天给你们说的<a class='k' href='http://m.weibo.cn/k/圣诞快乐?from=feed'>#圣诞快乐#</a> …反正都是一如既往地没有什么特别的<a class='k' href='http://m.weibo.cn/k/圣诞节?from=feed'>#圣诞节#</a> ꒰╬•᷅д•᷄╬꒱ ​​​",
    "textLength": 176,
    "thumbnail_pic": "http://ww4.sinaimg.cn/thumbnail/b5ff8eb1gw1ez5ceoiuqmj20dc0hsjth.jpg",
    "user": {
      "cover_image_phone": "http://ww1.sinaimg.cn/crop.0.0.640.640.640/549d0121tw1egm1kjly3jj20hs0hsq4f.jpg",
      "description": "momo哒！~合作联系，商务：business@snh48.com 021-66075351 影视：yingshi@snh48.com 021-66078718*819 综艺：zongyi@snh48.com 021-66078718*821",
      "follow_count": 201,
      "follow_me": false,
      "followers_count": 475619,
      "following": false,
      "gender": "f",
      "id": 3053424305,
      "mbrank": 6,
      "mbtype": 12,
      "profile_image_url": "http://tva4.sinaimg.cn/crop.6.0.499.499.180/b5ff8eb1jw8f9g0xrj1doj20e80dvdg7.jpg",
      "profile_url": "http://m.weibo.cn/u/3053424305?uid=3053424305&luicode=10000011&lfid=1076033053424305",
      "screen_name": "SNH48-莫寒",
      "statuses_count": 1910,
      "urank": 37,
      "verified": true,
      "verified_reason": "人气偶像团体SNH48成员 莫寒",
      "verified_type": 0,
      "verified_type_ext": 0
    },
    "visible": {
      "list_id": 0,
      "type": 0
    }
  },
  "openurl": "",
  "scheme": "http://m.weibo.cn/status/D9byTBEQ2?mblogid=D9byTBEQ2&luicode=10000011&lfid=1076033053424305",
  "show_type": 0
}