{
  "card_type": 9,
  "itemid": "1076033053424305_-_4066404053151244",
  "mblog": {
    "_created_at": 1484989738,
    "attitudes_count": 3868,
    "bid": "ErRtjddMw",
    "bmiddle_pic": "http://wx2.sinaimg.cn/bmiddle/b5ff8eb1ly1fbyd3jqbf5j20ku0rsdig.jpg",
    "cardid": "vip_002",
    "comments_count": 1586,
    "created_at": "01-21 17:08",
    "favorited": false,
    "id": "4066404053151244",
    "isLongText": true,
    "mblogtype": 0,
    "original_pic": "http://wx2.sinaimg.cn/large/b5ff8eb1ly1fbyd3jqbf5j20ku0rsdig.jpg",
    "pics": [
      {
        "geo": {
          "croped": false,
          "height": 480,
          "width": 360
        },
        "large": {
          "geo": {
            "croped": false,
            "height": "1000",
            "width": "750"
          },
          "size": "large",
          "url": "http://wx2.sinaimg.cn/large/b5ff8eb1ly1fbyd3jqbf5j20ku0rsdig.jpg"
        },
        "pid": "b5ff8eb1ly1fbyd3jqbf5j20ku0rsdig",
        "size": "orj360",
        "url": "http://wx2.sinaimg.cn/orj360/b5ff8eb1ly1fbyd3jqbf5j20ku0rsdig.jpg"
      },
      {
        "geo": {
          "croped": false,
          "height": 638,
          "width": 360
        },
        "large": {
          "geo": {
            "croped": false,
            "height": "800",
            "width": "451"
          },
          "size": "large",
          "url": "http://wx1.sinaimg.cn/large/b5ff8eb1ly1fbyd3j8nfcj20cj0m8tbn.jpg"
        },
        "pid": "b5ff8eb1ly1fbyd3j8nfcj20cj0m8tbn",
        "size": "orj360",
        "url": "http://wx1.sinaimg.cn/orj360/b5ff8eb1ly1fbyd3j8nfcj20cj0m8tbn.jpg"
      }
    ],
    "reposts_count": 13730,
    "source": "ᙏ̤̫͚\" iPhone",
    "text": "我一直被认为是很会做菜的人。<br/>嗯，你们认为得并没有错，我在家的时候的确是挺会做菜的。我只是四年没有在家了而已。[二哈]<br/>所以突然通知我要做菜，我想了一想平时在中心的无敌简化版原汁原味食材减肥料理，那应该不算做菜。<i class=\"face face_1 icon_1\">[微笑]</i><br/>但是我一定是会做菜的。[摊手]<br/>机智的我特别问了一下，做好了是我们自 ​​​...<a href=\"/status/4066404053151244\">全文</a>",
    "textLength": 418,
    "thumbnail_pic": "http://wx2.sinaimg.cn/thumbnail/b5ff8eb1ly1fbyd3jqbf5j20ku0rsdig.jpg",
    "user": {
      "cover_image_phone": "http://ww1.sinaimg.cn/crop.0.0.640.640.640/549d0121tw1egm1kjly3jj20hs0hsq4f.jpg",
      "description": "momo哒！~合作联系，商务：business@snh48.com 021-66075351 影视：yingshi@snh48.com 021-66078718*819 综艺：zongyi@snh48.com 021-66078718*821",
      "follow_count": 201,
      "follow_me": false,
      "followers_count": 475619,
      "following": false,
      "gender": "f",
      "id": 3053424305,
      "mbrank": 6,
      "mbtype": 12,
      "profile_image_url": "http://tva4.sinaimg.cn/crop.6.0.499.499.180/b5ff8eb1jw8f9g0xrj1doj20e80dvdg7.jpg",
      "profile_url": "http://m.weibo.cn/u/3053424305?uid=3053424305&luicode=10000011&lfid=1076033053424305",
      "screen_name": "SNH48-莫寒",
      "statuses_count": 1910,
      "urank": 37,
      "verified": true,
      "verified_reason": "人气偶像团体SNH48成员 莫寒",
      "verified_type": 0,
      "verified_type_ext": 0
    },
    "visible": {
      "list_id": 0,
      "type": 0
    }
  },
  "openurl": "",
  "scheme": "http://m.weibo.cn/status/ErRtjddMw?mblogid=ErRtjddMw&luicode=10000011&lfid=1076033053424305",
  "show_type": 0
}